{
  "description": "数据请求成功",
  "status": "ok",
  "data": [
    {
      "label":"拔管原因",
      "value":"",
      "type":"radio",
      "name":"extubationReason",
      "options":[
        {
          "label":"计划内",
          "value":"计划内"
        },{
          "label":"计划外",
          "value":"计划外"
        }
      ],
      "default":"计划内",
      "actionValue":"计划外",
      "action":[
        {
          "children":[
            {
              "label":"计划外说明",
              "name":"unscheduledInstruction",
              "value":"",
              "type":"text"
            }
          ]
        }
      ]
    },
    {
      "label":"导管使用天数",
      "value":"",
      "type":"unit",
      "name":"useDays"
    },
    {
      "label":"B超结果",
      "value":"",
      "type":"radio",
      "name":"bresult",
      "options":[
        {
          "label":"有血栓",
          "value":"有血栓"
        },
        {
          "label":"无血栓",
          "value":"无血栓"
        }
      ],
      "default":"无血栓",
      "actionValue":"有血栓",
      "action":[
        {
          "children":[
            {
              "label":"抗凝治疗",
              "value":"",
              "type":"unit",
              "name":"disappear",
              "unit":"天血栓消失"
            }
          ]
        }
      ]
    },{
      "label":"应用导管期间并发症",
      "value":[],
      "type":"checkbox",
      "name":"complication",
      "options":[
        {
          "label":"无",
          "value":"无"
        },{
          "label":"静脉炎",
          "value":"静脉炎"
        },{
          "label":"渗血",
          "value":"渗血"
        },{
          "label":"渗液",
          "value":"渗液"
        },{
          "label":"过敏",
          "value":"过敏"
        },{
          "label":"导管部分脱出",
          "value":"导管部分脱出"
        },{
          "label":"堵管",
          "value":"堵管"
        },{
          "label":"血栓",
          "value":"血栓"
        },{
          "label":"导管断裂",
          "value":"导管断裂"
        },{
          "label":"异位",
          "value":"异位"
        }
      ]
      ,"default":"无"
    },{
      "hasBranch":false,
      "type":"radio",
      "name":"tubeSpecifications",
      "label":"导管规格",
      "value":"",
      "options":[
        {
          "label":"3F",
          "value":"3F"
        },
        {
          "label":"4F",
          "value":"4F"
        },
        {
          "label":"5F",
          "value":"5F"
        },
        {
          "label":"不详",
          "value":"不详"
        }
      ]
    },
    {
      "hasBranch":false,
      "type":"radio",
      "name":"tubePosition",
      "label":"导管部位",
      "value":"",
      "options":[
        {
          "label":"左侧",
          "value":"左侧"
        },
        {
          "label":"右侧",
          "value":"右侧"
        },
        {
          "label":"肘上",
          "value":"肘上"
        },
        {
          "label":"肘下",
          "value":"肘下"
        },
        {
          "label":"其他",
          "value":"其他"
        }
      ],
      "actionValue":"其他",
      "action":[
        {
          "children":[
            {
              "type":"text",
              "name":"otherTubePosition",
              "label":"其他导管部位",
              "value":""
            }
          ]
        }
      ]
    },
    {
      "label":"拔管时间",
      "value":"",
      "type":"datetime",
      "name":"extubationTime",
      "require":true,
      "requireTime":true
    },
    {
      "label":"拔管护士",
      "value":"",
      "type":"text",
      "name":"extubationNurse"
    }
  ]
}